infrastructure_manager_sync/__init__.py
infrastructure_manager_sync/filtersets.py
infrastructure_manager_sync/forms.py
infrastructure_manager_sync/graphql.py
infrastructure_manager_sync/models.py
infrastructure_manager_sync/navigation.py
infrastructure_manager_sync/search.py
infrastructure_manager_sync/tables.py
infrastructure_manager_sync/template_content.py
infrastructure_manager_sync/urls.py
infrastructure_manager_sync/views.py
infrastructure_manager_sync/api/__init__.py
infrastructure_manager_sync/api/serializers.py
infrastructure_manager_sync/api/urls.py
infrastructure_manager_sync/api/views.py
infrastructure_manager_sync/migrations/0001_initial.py
infrastructure_manager_sync/migrations/0002_infrastructuremanagersyncvminfo_ims.py
infrastructure_manager_sync/migrations/0003_alter_infrastructuremanagersyncvminfo_ims.py
infrastructure_manager_sync/migrations/0004_infrastructuremanagersynchostinfo.py
infrastructure_manager_sync/migrations/0005_infrastructuremanagersynchostinfo_ims.py
infrastructure_manager_sync/migrations/0006_alter_infrastructuremanagersynchostinfo_options_and_more.py
infrastructure_manager_sync/migrations/0007_infrastructuremanagersync_version.py
infrastructure_manager_sync/migrations/0008_rename_physical_cpu_cores_infrastructuremanagersynchostinfo_cpu_type_and_more.py
infrastructure_manager_sync/migrations/0009_infrastructuremanagersynchostinfo_core_per_cpu.py
infrastructure_manager_sync/migrations/0010_infrastructuremanagersync_last_successful_sync.py
infrastructure_manager_sync/migrations/0011_infrastructuremanagersync_update_prio.py
infrastructure_manager_sync/migrations/0012_alter_infrastructuremanagersyncvminfo_financial_info_and_more.py
infrastructure_manager_sync/migrations/0013_alter_infrastructuremanagersyncvminfo_financial_info_and_more.py
infrastructure_manager_sync/migrations/0014_infrastructuremanagersyncvminfo_backup_status_and_more.py
infrastructure_manager_sync/migrations/0015_alter_infrastructuremanagersyncvminfo_last_backup.py
infrastructure_manager_sync-0.6.1.dist-info/METADATA
infrastructure_manager_sync-0.6.1.dist-info/WHEEL
infrastructure_manager_sync-0.6.1.dist-info/top_level.txt
infrastructure_manager_sync-0.6.1.dist-info/RECORD
