Metadata-Version: 2.4
Name: infrastructure_manager_sync
Version: 0.6.1
Summary: Netbox ims plugin
Author-email: Mattijs Vanhaverbeke <author@example.com>
Classifier: Intended Audience :: Developers
Classifier: Natural Language :: English
Classifier: Programming Language :: Python :: 3 :: Only
Classifier: Programming Language :: Python :: 3.10
Classifier: Programming Language :: Python :: 3.11
Classifier: Programming Language :: Python :: 3.12
Requires-Python: >=3.10.0
